terminal_formatter/__init__.py
terminal_formatter/formatter.py
terminal_formatter/py.typed
terminal_formatter-0.0.2.dist-info/LICENSE
terminal_formatter-0.0.2.dist-info/METADATA
terminal_formatter-0.0.2.dist-info/WHEEL
terminal_formatter-0.0.2.dist-info/top_level.txt
terminal_formatter-0.0.2.dist-info/RECORD
