Metadata-Version: 2.1
Name: terminal-formatter
Version: 0.0.2
Summary: Simple terminal text formatter that helps with printing pretty stuff
Home-page: https://github.com/rlipperts/formatter
Author: Ruben Lipperts
Author-email: 
Classifier: Programming Language :: Python :: 3.9
Classifier: License :: OSI Approved :: MIT License
Classifier: Operating System :: OS Independent
Classifier: Topic :: Text Processing :: General
Requires-Python: ~=3.9
License-File: LICENSE
Requires-Dist: pprintpp
Requires-Dist: colored
Provides-Extra: test
Requires-Dist: pytest ; extra == 'test'
Requires-Dist: pytest-timeout ; extra == 'test'
Requires-Dist: flake8 ; extra == 'test'
Requires-Dist: pylint ; extra == 'test'
Requires-Dist: mypy ; extra == 'test'
